draw_mempool/__init__.py
draw_mempool/draw_mempool.py
draw_mempool/rpc.py
draw_mempool-0.1.2.dist-info/LICENSE.txt
draw_mempool-0.1.2.dist-info/METADATA
draw_mempool-0.1.2.dist-info/WHEEL
draw_mempool-0.1.2.dist-info/entry_points.txt
draw_mempool-0.1.2.dist-info/top_level.txt
draw_mempool-0.1.2.dist-info/RECORD
