Metadata-Version: 2.1
Name: draw-mempool
Version: 0.1.2
Summary: Draw the Bitcoin Core mempool
Home-page: https://github.com/conscott/draw_mempool
Author: conscott
Author-email: conor.r.scott.88@gmail.com
License: UNKNOWN
Keywords: bitcoin mempool
Platform: UNKNOWN
Classifier: Programming Language :: Python :: 3.4
Classifier: Programming Language :: Python :: 3.5
Classifier: Programming Language :: Python :: 3.6
Classifier: License :: OSI Approved :: MIT License
Classifier: Operating System :: OS Independent
Requires-Python: >=3.4
Requires-Dist: matplotlib (==2.1.2)
Requires-Dist: networkx (==2.1)
